mkdocs_bulma_classes_plugin/__init__.py
mkdocs_bulma_classes_plugin/plugin.py
mkdocs_bulma_classes_plugin/regexs/__init__.py
mkdocs_bulma_classes_plugin/regexs/regex.py
mkdocs_bulma_classes_plugin-1.0.0b7.dist-info/METADATA
mkdocs_bulma_classes_plugin-1.0.0b7.dist-info/entry_points.txt
mkdocs_bulma_classes_plugin-1.0.0b7.dist-info/WHEEL
mkdocs_bulma_classes_plugin-1.0.0b7.dist-info/LICENSE
mkdocs_bulma_classes_plugin-1.0.0b7.dist-info/RECORD
