Metadata-Version: 2.1
Name: mkdocs-bulma-classes-plugin
Version: 1.0.0b7
Summary: Add support to Bulma css framework in Mkdocs
Home-page: https://daniele-tentoni.github.io/mkdocs-bulma-classes-plugin
License: MIT
Keywords: mkdocs,plugin
Author: Daniele Tentoni
Author-email: daniele.tentoni.1996@gmail.com
Requires-Python: >=3.10,<4.0
Classifier: License :: OSI Approved :: MIT License
Classifier: Programming Language :: Python :: 3
Classifier: Programming Language :: Python :: 3.10
Classifier: Programming Language :: Python :: 3.11
Project-URL: Repository, https://github.com/daniele-tentoni/mkdocs-bulma-classes-plugin
